AirtablePy/__init__.py
AirtablePy/airtable_filters.yml
AirtablePy/api.py
AirtablePy/query.py
AirtablePy/utils.py
AirtablePy-0.1.3.dist-info/LICENSE
AirtablePy-0.1.3.dist-info/METADATA
AirtablePy-0.1.3.dist-info/WHEEL
AirtablePy-0.1.3.dist-info/top_level.txt
AirtablePy-0.1.3.dist-info/RECORD
