Metadata-Version: 2.1
Name: AirtablePy
Version: 0.1.3
Summary: Python API to interact with Airtable
Home-page: https://github.com/Spill-Tea/AirtablePy
Author: Spill-Tea
Author-email: spillthetea917@gmail.com
License: UNKNOWN
Project-URL: Bug Reports, https://github.com/Spill-Tea/AirtablePy/issues
Keywords: airtable api requests
Platform: UNKNOWN
Classifier: Development Status :: 4 - Beta
Classifier: Intended Audience :: Developers
Classifier: License :: OSI Approved :: MIT License
Classifier: Programming Language :: Python :: 3
Requires-Python: >=3.8
License-File: LICENSE
Requires-Dist: requests
Requires-Dist: responses
Requires-Dist: pandas
Requires-Dist: pyyaml
